msaDocModels/__init__.py
msaDocModels/health.py
msaDocModels/msg.py
msaDocModels/openapi.py
msaDocModels/pubsub.py
msaDocModels/scheduler.py
msaDocModels/sdu.py
msaDocModels/utils/__init__.py
msaDocModels/utils/htmlutils.py
msaDocModels/wdc.py
msaDocModels/wfl.py
msadocmodels-0.0.114.dist-info/METADATA
msadocmodels-0.0.114.dist-info/WHEEL
msadocmodels-0.0.114.dist-info/RECORD
