Metadata-Version: 2.1
Name: msaDocModels
Version: 0.0.114
Summary: MSA Document Pydantic Models and Schemas, used to store Parser, NLP, NLU and AI results for processed documents
Author: Stefan Welcker
Requires-Python: >=3.9.0,<3.11
Classifier: Programming Language :: Python :: 3
Classifier: Programming Language :: Python :: 3.9
Classifier: Programming Language :: Python :: 3.10
Requires-Dist: bson (==0.5.10)
Requires-Dist: genson (==1.2.2)
Requires-Dist: loguru (==0.6.0)
Requires-Dist: lxml (==4.9.2)
Requires-Dist: multidict (==6.0.4)
Requires-Dist: pydantic (==1.9.2)
